devtools_sitecustomize/__init__.py
devtools_sitecustomize-0.1.10.dist-info/WHEEL
devtools_sitecustomize-0.1.10.dist-info/entry_points.txt
devtools_sitecustomize-0.1.10.dist-info/METADATA
devtools_sitecustomize-0.1.10.dist-info/RECORD
