Metadata-Version: 2.3
Name: devtools-sitecustomize
Version: 0.1.10
Summary: Add your description here
Requires-Dist: devtools>=0.12.2
Requires-Dist: sitecustomize-entrypoints>=1.1.0
Requires-Python: >=3.13
Project-URL: GitHub, https://github.com/5j9/devtools-sitecustomize
